ambisafe_tenant/__init__.py
ambisafe_tenant/account.py
ambisafe_tenant/auth.py
ambisafe_tenant/client.py
ambisafe_tenant/crypt.py
ambisafe_tenant/exc.py
ambisafe_tenant/icap.py
ambisafe_tenant/recovery.py
ambisafe_tenant/utils.py
test/__init__.py
test/test.py
ambisafe_tenant-0.1.5.dist-info/LICENSE
ambisafe_tenant-0.1.5.dist-info/METADATA
ambisafe_tenant-0.1.5.dist-info/WHEEL
ambisafe_tenant-0.1.5.dist-info/top_level.txt
ambisafe_tenant-0.1.5.dist-info/RECORD
