Metadata-Version: 2.1
Name: ambisafe-tenant
Version: 0.1.5
Summary: Ambisafe-tenant server client library
Home-page: https://github.com/Ambisafe/ambisafe_tenant_client
Author: Kirill Pisarev
Author-email: kirill@ambisafe.co
License: UNKNOWN
Download-URL: https://github.com/Ambisafe/ambisafe_tenant_client/get/v0.1.5.zip
Keywords: ambisafe,ethereum,etoken
Platform: UNKNOWN
Classifier: Intended Audience :: Developers
Requires-Dist: requests (>=2.7.0)
Requires-Dist: python-stdnum (==1.4)
Requires-Dist: pycoin (==0.62)
Requires-Dist: mock (>=1.3.0)
Requires-Dist: pysha3 (==0.3)
Requires-Dist: bitcoin (==1.1.42)
